README.md
setup.py
pylexo/__init__.py
pylexo/__main__.py
pylexo/base.py
pylexo/input.py
pylexo/lambda_response.py
pylexo/runtime_response.py
pylexo/stub_generator.py
pylexo.egg-info/PKG-INFO
pylexo.egg-info/SOURCES.txt
pylexo.egg-info/dependency_links.txt
pylexo.egg-info/entry_points.txt
pylexo.egg-info/requires.txt
pylexo.egg-info/top_level.txt
pylexo.egg-info/zip-safe