Metadata-Version: 1.0
Name: pylexo
Version: 0.6.0
Summary: Pythonic Lex Object (PyLexO)
Home-page: https://github.com/wavycloud/pylexo
Author: WavyCloud
Author-email: UNKNOWN
License: MIT License
Keywords: aws python lex lambda
Platform: UNKNOWN
